{
    "upstream": {
        "Official": {
            "name": "Julialang.org",
            "urls": [
                "https://julialang-s3.julialang.org/bin/$sys/$arch/$minor_version/$filename"
            ],
            "latest_urls": [
                "https://julialangnightlies-s3.julialang.org/bin/$sys/$arch/$latest_filename"
            ]
        },
        "BFSU": {
            "name": "Beijing Foreign Studies University",
            "urls": [
                "https://mirrors.bfsu.edu.cn/julia-releases/bin/$sys/$arch/$minor_version/$filename"
            ],
            "latest_urls": [
                ""
            ]
        },
        "TUNA": {
            "name": "Tsinghua University TUNA Association",
            "urls": [
                "https://mirrors.tuna.tsinghua.edu.cn/julia-releases/bin/$sys/$arch/$minor_version/$filename"
            ],
            "latest_urls": [
                ""
            ]
        },
        "USTC": {
            "name": "University of Science and Technology of China",
            "urls": [
                "http://mirrors.ustc.edu.cn/julia-releases/bin/$sys/$arch/$minor_version/$filename"
            ],
            "latest_urls": [
                ""
            ]
        },
        "SJTUG": {
             "name": "Shanghai Jiao Tong University Linux User Group",
             "urls": [
                 "https://mirrors.sjtug.sjtu.edu.cn/julia-releases/bin/$sys/$arch/$minor_version/$filename"
             ],
             "latest_urls": [
                 ""
             ]
         }
    }
}

